{
	"name": "priyasqlserverLS2datasetParameters",
	"properties": {
		"activities": [
			{
				"name": "Copy data1",
				"type": "Copy",
				"dependsOn": [],
				"policy": {
					"timeout": "0.12:00:00",
					"retry": 0,
					"retryIntervalInSeconds": 30,
					"secureOutput": false,
					"secureInput": false
				},
				"userProperties": [],
				"typeProperties": {
					"source": {
						"type": "SqlServerSource",
						"queryTimeout": "02:00:00",
						"partitionOption": "None"
					},
					"sink": {
						"type": "SqlServerSink",
						"writeBehavior": "insert",
						"sqlWriterUseTableLock": false
					},
					"enableStaging": false,
					"translator": {
						"type": "TabularTranslator",
						"typeConversion": true,
						"typeConversionSettings": {
							"allowDataTruncation": true,
							"treatBooleanAsNumber": false
						}
					}
				},
				"inputs": [
					{
						"referenceName": "dataset2priyasqlserverLs",
						"type": "DatasetReference",
						"parameters": {
							"tableName": {
								"value": "@pipeline().parameters.sourceTableFromPipeline",
								"type": "Expression"
							},
							"dbNameinDataSet": {
								"value": "@pipeline().parameters.dbNameFrompipeline",
								"type": "Expression"
							}
						}
					}
				],
				"outputs": [
					{
						"referenceName": "dataset2priyasqlserverLs",
						"type": "DatasetReference",
						"parameters": {
							"tableName": {
								"value": "@pipeline().parameters.destinationTableFromPipeline",
								"type": "Expression"
							},
							"dbNameinDataSet": {
								"value": "@pipeline().parameters.dbNameFrompipeline",
								"type": "Expression"
							}
						}
					}
				]
			}
		],
		"parameters": {
			"sourceTableFromPipeline": {
				"type": "string"
			},
			"dbNameFrompipeline": {
				"type": "string"
			},
			"destinationTableFromPipeline": {
				"type": "string"
			}
		},
		"annotations": []
	}
}