{
	"name": "DelimitedText7",
	"properties": {
		"linkedServiceName": {
			"referenceName": "adf2rgcontaineremp",
			"type": "LinkedServiceReference"
		},
		"annotations": [],
		"type": "DelimitedText",
		"typeProperties": {
			"location": {
				"type": "AzureBlobStorageLocation",
				"folderPath": "log",
				"container": "empdb"
			},
			"columnDelimiter": ",",
			"escapeChar": "\\",
			"firstRowAsHeader": true,
			"quoteChar": "\""
		},
		"schema": [
			{
				"name": "FirstName",
				"type": "String"
			},
			{
				"name": "LastName",
				"type": "String"
			},
			{
				"name": "Salary",
				"type": "String"
			},
			{
				"name": "Occupation",
				"type": "String"
			},
			{
				"name": "Department",
				"type": "String"
			}
		]
	}
}